README.md
setup.py
lagrunge82_test_sdk/__init__.py
lagrunge82_test_sdk/api_client.py
lagrunge82_test_sdk/exceptions.py
lagrunge82_test_sdk.egg-info/PKG-INFO
lagrunge82_test_sdk.egg-info/SOURCES.txt
lagrunge82_test_sdk.egg-info/dependency_links.txt
lagrunge82_test_sdk.egg-info/requires.txt
lagrunge82_test_sdk.egg-info/top_level.txt
lagrunge82_test_sdk/components/__init__.py
lagrunge82_test_sdk/components/models.py
lagrunge82_test_sdk/utils/__init__.py
tests/__init__.py
tests/test_lagrunge82_test_sdk.py