Metadata-Version: 2.1
Name: lagrunge82-test-sdk
Version: 0.3
Summary: Python SDK for accessing OpenWeatherMap API
Home-page: https://github.com/Lagrunge82/lagrunge82_test_sdk
Author: Lagrunge
Author-email: lagrunge82@gmail.com
License: UNKNOWN
Platform: UNKNOWN
